.class public Test
.super java/lang/Object


.field a I
.field helloWorld Ljava/lang/String;


.method public <init>()V
.limit stack 2
.limit locals 1
aload_0
invokespecial java/lang/Object/<init>()V
aload 0
ldc 3
putfield Test/a I
aload 0
ldc "globalvariableoverschrijving:"
putfield Test/helloWorld Ljava/lang/String;
return
.end method




.method public static main([Ljava/lang/String;)V
.limit stack 3
.limit locals 1
new Test
dup
invokespecial Test/<init>()V
invokevirtual Test/myMethod()V
return
.end method


.method public method2(I)V
.limit stack 3
.limit locals 4
iload 1
aload_0
ldc 2
invokevirtual Test/method3(I)I
iadd
istore 2
getstatic java/lang/System.out Ljava/io/PrintStream;
new java/lang/StringBuilder
dup
invokespecial java/lang/StringBuilder/<init>()V
ldc "print int x: "
invokevirtual java/lang/StringBuilder/append(Ljava/lang/String;)Ljava/lang/StringBuilder;
iload 2
invokevirtual java/lang/StringBuilder/append(I)Ljava/lang/StringBuilder;
invokevirtual java/lang/StringBuilder/toString()Ljava/lang/String;
invokevirtual java/io/PrintStream/println(Ljava/lang/String;)V
return
.end method


.method public method3(I)I
.limit stack 7
.limit locals 5
ldc 0
istore 2
goto forCondition_1
forIDCrement_1:
iinc 2 1
forCondition_1:
iload 2
ldc 10
if_icmpge endFor_1
beginFor_1:
iload 2
iload 1
imul
istore 3
iload 3
ldc 4
if_icmple endif_1
#_1_code_block_1: 
getstatic java/lang/System.out Ljava/io/PrintStream;
new java/lang/StringBuilder
dup
invokespecial java/lang/StringBuilder/<init>()V
iload 3
invokevirtual java/lang/StringBuilder/append(I)Ljava/lang/StringBuilder;
invokevirtual java/lang/StringBuilder/toString()Ljava/lang/String;
invokevirtual java/io/PrintStream/println(Ljava/lang/String;)V
goto endif_1
endif_1:
goto forIDCrement_1
endFor_1:
getstatic java/lang/System.out Ljava/io/PrintStream;
new java/lang/StringBuilder
dup
invokespecial java/lang/StringBuilder/<init>()V
aload 0
getfield Test/helloWorld Ljava/lang/String;
invokevirtual java/lang/StringBuilder/append(Ljava/lang/String;)Ljava/lang/StringBuilder;
invokevirtual java/lang/StringBuilder/toString()Ljava/lang/String;
invokevirtual java/io/PrintStream/println(Ljava/lang/String;)V
aload 0
new java/util/Scanner
dup
getstatic	java/lang/System.in Ljava/io/InputStream;
invokespecial	java/util/Scanner/<init>(Ljava/io/InputStream;)V
invokevirtual java/util/Scanner/nextLine()Ljava/lang/String;
putfield Test/helloWorld Ljava/lang/String;
ldc 3
ireturn
.end method


.method public myMethod()V
.limit stack 5
.limit locals 1
aload_0
ldc 1
invokevirtual Test/method2(I)V
getstatic java/lang/System.out Ljava/io/PrintStream;
new java/lang/StringBuilder
dup
invokespecial java/lang/StringBuilder/<init>()V
aload 0
getfield Test/helloWorld Ljava/lang/String;
invokevirtual java/lang/StringBuilder/append(Ljava/lang/String;)Ljava/lang/StringBuilder;
invokevirtual java/lang/StringBuilder/toString()Ljava/lang/String;
invokevirtual java/io/PrintStream/println(Ljava/lang/String;)V
return
.end method


